opencv_tk/__init__.py
opencv_tk/__init__.pyi
opencv_tk/picturebox.py
opencv_tk/picturebox.pyi
opencv_tk/py.typed
opencv_tk-1.2.0.dist-info/licenses/LICENSE
opencv_tk-1.2.0.dist-info/METADATA
opencv_tk-1.2.0.dist-info/WHEEL
opencv_tk-1.2.0.dist-info/top_level.txt
opencv_tk-1.2.0.dist-info/RECORD
