Metadata-Version: 2.4
Name: opencv_tk
Version: 1.2.0
Summary: A Tkinter PictureBox widget for displaying an OpenCV image.
Author-email: John Bolkcom <johnbolk6502@gmail.com>
License-Expression: MIT
Project-URL: Homepage, https://github.com/johnbolk/opencv_tk.git
Keywords: Tkinter,OpenCV,PictureBox
Classifier: Programming Language :: Python :: 3
Classifier: Operating System :: OS Independent
Classifier: Intended Audience :: Developers
Requires-Python: >=3.7
License-File: LICENSE
Requires-Dist: pillow>=9.5.0
Dynamic: license-file
